LICENSE
MANIFEST.in
README.md
setup.py
proharmed/__init__.py
proharmed/fasta_grepper.py
proharmed/filter_ids.py
proharmed/intersection_analysis.py
proharmed/map_orthologs.py
proharmed/reduce_genenames.py
proharmed/remap_genenames.py
proharmed.egg-info/PKG-INFO
proharmed.egg-info/SOURCES.txt
proharmed.egg-info/dependency_links.txt
proharmed.egg-info/requires.txt
proharmed.egg-info/top_level.txt
proharmed/mq_utils/HGNC_mapping.py
proharmed/mq_utils/__init__.py
proharmed/mq_utils/logger.py
proharmed/mq_utils/mapping_handler.py
proharmed/mq_utils/plotting.py
proharmed/mq_utils/runner_utils.py