Metadata-Version: 2.1
Name: proharmed
Version: 0.0.6
Summary: Collection of scripts for ProHarMeD
Home-page: http://pypi.python.org/pypi/proharmed/
Author: Klaudia Adamowicz
Author-email: klaudia.adamowicz@uni-hamburg.de
License: LICENSE
Platform: UNKNOWN
Classifier: Programming Language :: Python :: 3.7
Classifier: Programming Language :: Python :: 3.8
Classifier: Programming Language :: Python :: 3.9
Classifier: Intended Audience :: Science/Research
Requires-Python: >=3.7
License-File: LICENSE
